{
  "ABORIGINALITY": "ABORIGINALITY",
  "ADDRESS": "ADDRESS",
  "AUDIO_INFORMATION": "AUDIO_INFORMATION",
  "AU_BANK_ACCOUNT": "BANK_ACCOUNT_NUMBER",
  "AU_DRIVERS_LICENCE": "DRIVERS_LICENCE",
  "AU_PASSPORT": "PASSPORT_NUMBER",
  "AU_PHONE": "MOBILE",
  "AU_TFN": "AU_TFN",
  "BSB": "BANK_ACCOUNT_NUMBER",
  "CAMERA_FOOTAGE_AUDIO": "CAMERA_FOOTAGE_AUDIO",
  "CARING_RESPONSIBILITIES": "CARING_RESPONSIBILITIES",
  "CENTRELINK_REFERENCE_NUMBER": "CENTRELINK_REFERENCE_NUMBER",
  "CITIZENSHIP_STATUS": "CITIZENSHIP_STATUS",
  "CONTRACT_TYPE": "CONTRACT_TYPE",
  "COOKIE_INFORMATION": "COOKIE_INFORMATION",
  "COUNSELLING_RECORDS": "COUNSELLING_RECORDS",
  "CREDIT_CARD_CVV": "PAYMENT_CARD_NUMBER",
  "CREDIT_CARD_EXPIRY": "CREDIT_CARD_EXPIRY",
  "CRIMINAL_RECORDS": "CRIMINAL_RECORDS",
  "DATE_OF_BIRTH": "DATE_OF_BIRTH",
  "DEVICE_ID": "DEVICE_ID",
  "DISABILITY_OR_SPECIFIC_CONDITION": "DISABILITY_OR_SPECIFIC_CONDITION",
  "EMAIL_ADDRESS": "EMAIL_ADDRESS",
  "EMPLOYEE_NUMBER": "EMPLOYEE_NUMBER",
  "EMPLOYMENT_INFORMATION": "EMPLOYMENT_INFORMATION",
  "FACIAL_RECOGNITION": "FACIAL_RECOGNITION",
  "FINGERPRINT": "FINGERPRINT",
  "GENDER": "GENDER",
  "GEOLOCATION_INFORMATION": "GEOLOCATION_INFORMATION",
  "HASHED_PAYMENT_CARD_NUMBER": "HASHED_PAYMENT_CARD_NUMBER",
  "IHI": "IHI",
  "IP_ADDRESS": "IP_ADDRESS",
  "LATITUDE": "LATITUDE",
  "LONGITUDE": "LONGITUDE",
  "MARITAL_STATUS": "MARITAL_STATUS",
  "MEDICAL_CERTIFICATE": "MEDICAL_CERTIFICATE",
  "MEDICAL_INFORMATION": "MEDICAL_INFORMATION",
  "MEDICARE_EXPIRY": "MEDICARE_EXPIRY",
  "MEDICARE_NUMBER": "MEDICARE_NUMBER",
  "MILITARY_VETERAN_STATUS": "MILITARY_VETERAN_STATUS",
  "NATIONALITY": "NATIONALITY",
  "NATIONAL_IDENTITY_CARD": "NATIONAL_IDENTITY_CARD",
  "NEXT_OF_KIN": "NEXT_OF_KIN",
  "NUMBER_PLATE": "NUMBER_PLATE",
  "PASSPORT_EXPIRY": "PASSPORT_EXPIRY",
  "PASSPORT_START_DATE": "PASSPORT_START_DATE",
  "PAYMENT_CARD_NUMBER": "PAYMENT_CARD_NUMBER",
  "PENSION_CARD_NUMBER": "PENSION_CARD_NUMBER",
  "PERSON": "PERSON",
  "PERSONAL_DEBT": "PERSONAL_DEBT",
  "PERSONNEL_NUMBER": "PERSONNEL_NUMBER",
  "PRONOUN": "PRONOUN",
  "RACIAL_ETHNIC_ORIGIN": "RACIAL_ETHNIC_ORIGIN",
  "RELIGION_BELIEF": "RELIGION_BELIEF",
  "SALARY": "SALARY",
  "SALARY_WAGE_EXPECTATION": "SALARY_WAGE_EXPECTATION",
  "SANCTIONS": "SANCTIONS",
  "SCHOLARSHIP": "SCHOLARSHIP",
  "SEXUAL_ORIENTATION": "SEXUAL_ORIENTATION",
  "SIGNATURE": "SIGNATURE",
  "SOCIAL_MEDIA_ACCOUNT": "SOCIAL_MEDIA_ACCOUNT",
  "SOCIAL_MEDIA_HISTORY": "SOCIAL_MEDIA_HISTORY",
  "SOCIAL_MEDIA_ID": "SOCIAL_MEDIA_ID",
  "SOCIO_ECONOMIC_STATUS": "SOCIO_ECONOMIC_STATUS",
  "SPECIAL_CONSIDERATION": "SPECIAL_CONSIDERATION",
  "STUDENT_ID": "STUDENT_ID",
  "SUBJECT_RESULTS": "SUBJECT_RESULTS",
  "UAC_ID": "UAC_ID",
  "USERNAME": "USERNAME",
  "USI": "USI",
  "VEHICLE_REGO": "VEHICLE_REGO",
  "VOICE_RECOGNITION": "VOICE_RECOGNITION",
  "WAM_SCORE": "WAM_SCORE",
  "WEBSITE_HISTORY": "WEBSITE_HISTORY",
  "WORKERS_COMPENSATION_CLAIM": "WORKERS_COMPENSATION_CLAIM",
  "WORK_EMAIL": "WORK_EMAIL",
  "WORK_PHONE": "WORK_PHONE"
}
